potterworld/__init__.py
potterworld/sub1/__init__.py
potterworld/sub1/hogwarts.py
potterworld/sub1/sorting_hat_song.py
potterworld/sub1/wizard.py
potterworld/sub2/__init__.py
potterworld/sub2/duel.py
potterworld/sub2/learn_spells.py
potterworld/sub2/quidditch.py
potterworld/sub2/spells.py
potterworld-0.1.dist-info/LICENSE.txt
potterworld-0.1.dist-info/METADATA
potterworld-0.1.dist-info/WHEEL
potterworld-0.1.dist-info/top_level.txt
potterworld-0.1.dist-info/RECORD
