Metadata-Version: 2.1
Name: potterworld
Version: 0.1
Summary: A journey into the wizarding world
Home-page: https://github.com/cfbanks/data-533-lab4
Author: Connor and Naveen
Author-email: connorfairbanks@gmail.com
License: MIT
Platform: UNKNOWN
